{
    "pages": {
        "home": "true",
        "about": "true",
        "projects": "true",
        "experience": "true",
        "education": "true",
        "skills": "true",
        "contact": "true"
    },
    "name": "Serhii Untilov",
    "email": "s.untilov@gmail.com",
    "site": {
        "link": "https://untilov.com.ua",
        "label": "Untilov.com.ua"
    },
    "job": "Full-stack Web Developer",
    "brief": "Hi, I'm Serhii Untilov. A Full-stack Web Developer based in Irpin, Ukraine.",
    "socialMedia": {
        "linkedin": "https://www.linkedin.com/in/serhiiuntilov",
        "github": "https://github.com/serhii-untilov",
        "facebook": "https://www.facebook.com/s.untilov",
        "harvardx": "https://courses.edx.org/certificates/631ec2cdcc6145aabcc6d5674762f51c"
    },
    "techStack": [
        "HTML5",
        "CSS3",
        "Tailwind CSS",
        "Material UI",
        "JavaScript",
        "TypeScript",
        "React",
        "Next.js",
        "NestJS",
        "TypeORM",
        "Django",
        "Postgres",
        "Docker",
        "Python"
    ],
    "about": {
        "title": "Full-stack Web Developer based in Irpin, Ukraine",
        "description": [
            "My name is Serhii, and I'm a Full-stack Web Developer. My mission is to create and develop fully functional, robust web applications for users.",
            "Currently, my main stack consists of React/Nest.js, combined with TypeScript, TypeORM, PostgreSQL, and Docker.",
            "I have over 10 years of experience developing web and desktop applications in product-oriented and project-oriented companies that provide B2B solutions for small and medium businesses and government agencies.",
            "I solved problems in complex schemes of relational databases and multi-tenant software architectures.",
            "Lately, I've been focusing on full-stack web development and end-to-end software deployment."
        ]
    },
    "projects": [
        {
            "title": "Payroll SMB",
            "description": "Payroll SMB application provides a **solution for employers and employees to calculate salary** and taxes based on laws for chosen country",
            "pageUrl": "",
            "techStack": [
                "TypeScript",
                "NestJS",
                "TypeORM",
                "Postgres",
                "React",
                "Material UI",
                "Docker"
            ],
            "sourceUrl": "https://github.com/serhii-untilov/Payroll",
            "demoUrl": ""
        }
    ],
    "experience": [
        {
            "title": "Programmer, Team lead",
            "company": "Alliance Solution",
            "place": "Kyiv, Ukraine",
            "description": "Development of the A5 Tariffication project for Educational organizations",
            "responsibilities": [
                "analysis of customer requirements",
                "product design, project management",
                "programming, team management",
                "holding on presentations"
            ],
            "stack": [
                "Javascript",
                "UnityBase",
                "ExtJS",
                "SQL"
            ]
        }
    ],
    "education": [],
    "skills": []
}